{
  "hubs": [
    {
      "x": 0,
      "y": 38,
      "width": 1728,
      "height": 1079,
      "state": {
        "sidebar": {
          "width": 300,
          "expanded": [
            "/DriverStation/Joystick0/AxisValues",
            "/DriverStation/Joystick0/POVs",
            "/RealOutputs",
            "/PowerDistribution"
          ]
        },
        "tabs": {
          "selected": 1,
          "tabs": [
            {
              "type": 0,
              "path": "../docs/INDEX.md"
            },
            {
              "type": 1,
              "legends": {
                "left": {
                  "lockedRange": null,
                  "unitConversion": {
                    "type": null,
                    "factor": 1
                  },
                  "fields": [
                    {
                      "key": "/PowerDistribution/Voltage",
                      "color": "#2b66a2",
                      "show": true
                    }
                  ]
                },
                "discrete": {
                  "fields": []
                },
                "right": {
                  "lockedRange": null,
                  "unitConversion": {
                    "type": null,
                    "factor": 1
                  },
                  "fields": []
                }
              },
              "title": "Battery Voltage"
            },
            {
              "type": 3,
              "field": "/RealOutputs/Console",
              "title": "Console"
            }
          ]
        }
      }
    }
  ],
  "satellites": [],
  "version": "3.1.0"
}
